README.rst
setup.cfg
setup.py
pymodal/FRF_class.py
pymodal/__init__.py
pymodal/utils.py
pymodal.egg-info/PKG-INFO
pymodal.egg-info/SOURCES.txt
pymodal.egg-info/dependency_links.txt
pymodal.egg-info/requires.txt
pymodal.egg-info/top_level.txt
pymodal/ansys/__init__.py
pymodal/ansys/mesher.py
pymodal/ansys/preprocessor.py
pymodal/ansys/solver.py
pymodal/papergraph/__init__.py
pymodal/papergraph/imgplot.py
pymodal/papergraph/lineplot.py
pymodal/papergraph/surfplot.py
pymodal/papergraph/utils.py