Metadata-Version: 2.1
Name: pymodal
Version: 0.0.4
Summary: Modal analysis data management, simulation and storage tool
Home-page: https://github.com/grcarmenaty/pymodal
Author: Guillermo Reyes Carmenaty
Author-email: grcarmenaty@gmail.com
License: UNKNOWN
Download-URL: https://github.com/grcarmenaty/pymodal/archive/0.0.4.tar.gz
Platform: UNKNOWN
Classifier: Programming Language :: Python :: 3
Classifier: License :: OSI Approved :: MIT License 
Classifier: Operating System :: OS Independent
Requires-Python: >=3.6
Provides-Extra: dev
